postgres_metrics/__init__.py
postgres_metrics/apps.py
postgres_metrics/metrics.py
postgres_metrics/models.py
postgres_metrics/urls.py
postgres_metrics/views.py
postgres_metrics/management/__init__.py
postgres_metrics/management/commands/__init__.py
postgres_metrics/management/commands/pgm_list_metrics.py
postgres_metrics/management/commands/pgm_show_metric.py
postgres_metrics/static/postgres_metrics/css/base.css
postgres_metrics/static/postgres_metrics/css/rtl.css
postgres_metrics/templates/admin/index.html
postgres_metrics/templates/postgres_metrics/table.html
postgres_metrics/templatetags/__init__.py
postgres_metrics/templatetags/postgres_metrics.py
django_postgres_metrics-0.15.0.dist-info/AUTHORS
django_postgres_metrics-0.15.0.dist-info/LICENSE
django_postgres_metrics-0.15.0.dist-info/METADATA
django_postgres_metrics-0.15.0.dist-info/WHEEL
django_postgres_metrics-0.15.0.dist-info/top_level.txt
django_postgres_metrics-0.15.0.dist-info/RECORD
