Metadata-Version: 2.1
Name: django-postgres-metrics
Version: 0.15.0
Summary: A Django app that exposes a bunch of PostgreSQL database metrics.
Home-page: https://github.com/django-postgres-metrics/django-postgres-metrics
Author: Markus Holtermann
Author-email: info@markusholtermann.eu
License: BSD
Project-URL: CI, https://github.com/django-postgres-metrics/django-postgres-metrics/actions
Project-URL: Changelog, https://django-postgres-metrics.readthedocs.io/en/latest/changelog.html
Project-URL: Documentation, https://django-postgres-metrics.readthedocs.io/en/latest/index.html
Project-URL: Issues, https://github.com/django-postgres-metrics/django-postgres-metrics/issues
Platform: UNKNOWN
Classifier: Development Status :: 5 - Production/Stable
Classifier: Environment :: Web Environment
Classifier: Framework :: Django
Classifier: Framework :: Django :: 3.2
Classifier: Framework :: Django :: 4.1
Classifier: Framework :: Django :: 4.2
Classifier: Intended Audience :: Developers
Classifier: License :: OSI Approved :: BSD License
Classifier: Operating System :: OS Independent
Classifier: Programming Language :: Python
Classifier: Programming Language :: Python :: 3
Classifier: Programming Language :: Python :: 3.7
Classifier: Programming Language :: Python :: 3.8
Classifier: Programming Language :: Python :: 3.9
Classifier: Programming Language :: Python :: 3.10
Classifier: Programming Language :: Python :: 3.11
Requires-Python: >=3.7
License-File: LICENSE
License-File: AUTHORS
Requires-Dist: django-rich (>=1.0)
Provides-Extra: dev
Requires-Dist: pre-commit ; extra == 'dev'
Provides-Extra: docs
Requires-Dist: Django ; extra == 'docs'
Requires-Dist: psycopg2 ; extra == 'docs'
Requires-Dist: sphinx-rtd-theme (<2.0,>=1.0) ; extra == 'docs'
Requires-Dist: Sphinx (<5.0,>=4.0) ; extra == 'docs'
Provides-Extra: test
Requires-Dist: coverage[toml] (<6,>=5) ; extra == 'test'
Requires-Dist: Django ; extra == 'test'
Requires-Dist: selenium (==3.141.0) ; extra == 'test'
